README.md
setup.py
gitgang/__init__.py
gitgang/github.py
gitgang.egg-info/PKG-INFO
gitgang.egg-info/SOURCES.txt
gitgang.egg-info/dependency_links.txt
gitgang.egg-info/requires.txt
gitgang.egg-info/top_level.txt