Metadata-Version: 1.0
Name: gitgang
Version: 0.0.3
Summary: Reject pull-requests that are not from members of your gang.
Home-page: https://github.com/brockfanning/gitgang
Author: Brock Fanning
Author-email: brockfanning@gmail.com
License: MIT
Platform: UNKNOWN
